{
  "name": "SessionLedger",
  "image": "mcr.microsoft.com/devcontainers/rust:1-1-bookworm",
  "features": {
    "ghcr.io/devcontainers/features/common-utils:2": {
      "installZsh": false,
      "upgradePackages": false
    }
  },
  "customizations": {
    "vscode": {
      "extensions": [
        "rust-lang.rust-analyzer",
        "tamasfe.even-better-toml",
        "vadimcn.vscode-lldb",
        "fill-labs.dependi"
      ],
      "settings": {
        "editor.formatOnSave": true,
        "rust-analyzer.check.command": "clippy",
        "rust-analyzer.cargo.features": "all"
      }
    }
  },
  "postCreateCommand": "rustup component add rustfmt clippy && cargo fetch --locked",
  "forwardPorts": [8080],
  "portsAttributes": {
    "8080": {
      "label": "sl-daemon serve",
      "onAutoForward": "notify"
    }
  },
  "remoteUser": "vscode"
}
